planarenvs/.gitignore
planarenvs/__init__.py
planarenvs/mobile_base/.gitignore
planarenvs/mobile_base/__init__.py
planarenvs/mobile_base/envs/.gitignore
planarenvs/mobile_base/envs/__init__.py
planarenvs/mobile_base/envs/acc.py
planarenvs/mobile_base/envs/mobile_base_env.py
planarenvs/mobile_base/envs/vel.py
planarenvs/mobile_robot/.gitignore
planarenvs/mobile_robot/__init__.py
planarenvs/mobile_robot/envs/.gitignore
planarenvs/mobile_robot/envs/__init__.py
planarenvs/mobile_robot/envs/acc.py
planarenvs/mobile_robot/envs/mobile_robot_env.py
planarenvs/mobile_robot/envs/vel.py
planarenvs/n_link_reacher/.gitignore
planarenvs/n_link_reacher/__init__.py
planarenvs/n_link_reacher/envs/.gitignore
planarenvs/n_link_reacher/envs/__init__.py
planarenvs/n_link_reacher/envs/acc.py
planarenvs/n_link_reacher/envs/n_link_reacher_env.py
planarenvs/n_link_reacher/envs/vel.py
planarenvs/n_link_reacher/resources/.gitignore
planarenvs/n_link_reacher/resources/__init__.py
planarenvs/n_link_reacher/resources/accController.py
planarenvs/planar_common/.gitignore
planarenvs/planar_common/acc_env.py
planarenvs/planar_common/planar_env.py
planarenvs/planar_common/vel_env.py
planarenvs/point_robot/.gitignore
planarenvs/point_robot/__init__.py
planarenvs/point_robot/envs/.gitignore
planarenvs/point_robot/envs/__init__.py
planarenvs/point_robot/envs/acc.py
planarenvs/point_robot/envs/point_robot_env.py
planarenvs/point_robot/envs/vel.py
planarenvs/scenes/goal.py
planarenvs/scenes/obstacles.py
planarenvs/sensors/full_sensor.py
planarenvs/sensors/goal_sensor.py
planarenvs/sensors/obstacle_sensor.py
planarenvs/sensors/sensor_common.py
planarenvs-1.5.1.dist-info/METADATA
planarenvs-1.5.1.dist-info/WHEEL
planarenvs-1.5.1.dist-info/RECORD
