Metadata-Version: 2.3
Name: planarenvs
Version: 1.5.1
Summary: Lightweight open-ai gym environments for planar kinematic chains.
Author: Max Spahn
Author-email: m.spahn@tudelft.nl
Requires-Python: >=3.10,<4.0
Classifier: Programming Language :: Python :: 3
Classifier: Programming Language :: Python :: 3.10
Classifier: Programming Language :: Python :: 3.11
Classifier: Programming Language :: Python :: 3.12
Classifier: Programming Language :: Python :: 3.13
Requires-Dist: forwardkinematics (>=1.2.3,<2.0.0)
Requires-Dist: gym (>=0.26.0,<0.27.0)
Requires-Dist: mpscenes (>=0.4.6,<0.5.0)
Requires-Dist: pygame (>=2.6.1,<3.0.0)
Requires-Dist: pyglet (<2)
Requires-Dist: scipy (>=1.15.1,<2.0.0)
